[
	{
	  "idUsuario":"1",
	  "usuario":"nom",
	  "password":"askj24nem",
	  "nombre":"Juan Martin",
	  "apellido":"Del Potro",
	  "domicilio":"Medrano y Cordoba",
	  "fechaDeAlta":"01-01-2000",
	  "tipoDoc":"DNI",
	  "numeroDoc":"35000000",
	  "telefono":"48888888",
	  "idCategoria":"R1"
	},
	{
	  "id":"2",
	  "usuario":"onm",
	  "password":"asdjk4j5b",
	  "nombre":"David",
	  "apellido":"Nalbandian",
	  "domicilio":"Mozart 2300",
	  "fechaDeAlta":"01-01-2001",
	  "tipoDoc":"DNI",
	  "numeroDoc":"35000001",
	  "telefono":"48888886",
	  "idCategoria":"R2"
	},
	{
	  "id":"3",
	  "usuario":"mon",
	  "password":"uuhnmn6jh",
	  "nombre":"Gaston",
	  "apellido":"Gaudio",
	  "domicilio":"Cordoba 3000",
	  "fechaDeAlta":"01-01-2002",
	  "tipoDoc":"DNI",
	  "numeroDoc":"35000002",
	  "telefono":"48888889",
	  "idCategoria":"R3"
	}
]